django_afip/__init__.py
django_afip/admin.py
django_afip/apps.py
django_afip/clients.py
django_afip/crypto.py
django_afip/exceptions.py
django_afip/factories.py
django_afip/helpers.py
django_afip/models.py
django_afip/parsers.py
django_afip/pdf.py
django_afip/py.typed
django_afip/serializers.py
django_afip/signals.py
django_afip/version.py
django_afip/views.py
django_afip/fixtures/clientvatcondition.yaml
django_afip/fixtures/concepttype.yaml
django_afip/fixtures/currencytype.yaml
django_afip/fixtures/documenttype.yaml
django_afip/fixtures/optionaltype.yaml
django_afip/fixtures/receipttype.yaml
django_afip/fixtures/taxtype.yaml
django_afip/fixtures/vattype.yaml
django_afip/locale/es/LC_MESSAGES/django.mo
django_afip/locale/es/LC_MESSAGES/django.po
django_afip/management/commands/__init__.py
django_afip/management/commands/afipmetadata.py
django_afip/migrations/0001_squashed_0036_receiptpdf__client_address__blank.py
django_afip/migrations/0002_taxpayerextras.py
django_afip/migrations/0003_issuance_type_length.py
django_afip/migrations/0004_storages_and_help_texts.py
django_afip/migrations/0005_flatten_taxpayer_extras.py
django_afip/migrations/0006_delete_taxpayerextras.py
django_afip/migrations/0007_auto_20210409_1641.py
django_afip/migrations/0008_move_taxpayerprofile_to_pos.py
django_afip/migrations/0009_alter_pointofsales_issuance_type.py
django_afip/migrations/0010_alter_authticket_service.py
django_afip/migrations/0011_receiptentry_discount_and_more.py
django_afip/migrations/0012_optionaltype_optional_alter_code_in_generics.py
django_afip/migrations/0013_alter_receiptentry_quantity.py
django_afip/migrations/0014_alter_pointofsales_blocked_alter_taxpayer_logo.py
django_afip/migrations/0015_alter_taxpayer_logo.py
django_afip/migrations/0016_clientvatcondition_receipt_client_vat_condition.py
django_afip/migrations/__init__.py
django_afip/static/receipts/receipt.css
django_afip/templates/receipts/code_11.html
django_afip/templates/receipts/code_13.html
django_afip-13.2.2.dist-info/licenses/LICENCE
django_afip-13.2.2.dist-info/METADATA
django_afip-13.2.2.dist-info/WHEEL
django_afip-13.2.2.dist-info/top_level.txt
django_afip-13.2.2.dist-info/RECORD
